gradio_chatagui/__init__.py
gradio_chatagui/chatagui.py
gradio_chatagui/chatagui.pyi
gradio_chatagui/templates/component/Index-C16-Y8-n.js
gradio_chatagui/templates/component/_basePickBy-CGh-_FCk.js
gradio_chatagui/templates/component/_baseUniq-ZXbA32Vu.js
gradio_chatagui/templates/component/arc-C4rrzWeh.js
gradio_chatagui/templates/component/architectureDiagram-IEHRJDOE-YGD4zN0n.js
gradio_chatagui/templates/component/blockDiagram-JOT3LUYC-FySeC8wT.js
gradio_chatagui/templates/component/c4Diagram-VJAJSXHY-DmQoZsz0.js
gradio_chatagui/templates/component/channel-Df0jbHfj.js
gradio_chatagui/templates/component/chunk-4BMEZGHF-CtpLEWZg.js
gradio_chatagui/templates/component/chunk-A2AXSNBT-BU4QwRfi.js
gradio_chatagui/templates/component/chunk-AEK57VVT-Cuy322g9.js
gradio_chatagui/templates/component/chunk-D6G4REZN-CrPvI5hr.js
gradio_chatagui/templates/component/chunk-RZ5BOZE2-IWwRRzd2.js
gradio_chatagui/templates/component/chunk-XZIHB7SX-ce43fUZC.js
gradio_chatagui/templates/component/classDiagram-GIVACNV2-oZNbjSAa.js
gradio_chatagui/templates/component/classDiagram-v2-COTLJTTW-oZNbjSAa.js
gradio_chatagui/templates/component/clone-u_ySFJTF.js
gradio_chatagui/templates/component/cytoscape.esm-C2cgT2B2.js
gradio_chatagui/templates/component/dagre-OKDRZEBW-CTT71Dlt.js
gradio_chatagui/templates/component/diagram-SSKATNLV-CHTtac3I.js
gradio_chatagui/templates/component/diagram-VNBRO52H-DPkHSz_R.js
gradio_chatagui/templates/component/erDiagram-Q7BY3M3F-CVfxqi4b.js
gradio_chatagui/templates/component/flowDiagram-4HSFHLVR-C1RoOQpN.js
gradio_chatagui/templates/component/ganttDiagram-APWFNJXF-D2jIVajT.js
gradio_chatagui/templates/component/gitGraphDiagram-7IBYFJ6S-CSQwcB19.js
gradio_chatagui/templates/component/graph-hpW2uTm4.js
gradio_chatagui/templates/component/index.js
gradio_chatagui/templates/component/infoDiagram-PH2N3AL5-CwhCMdBW.js
gradio_chatagui/templates/component/init-DjUOC4st.js
gradio_chatagui/templates/component/journeyDiagram-U35MCT3I-DKzsArlq.js
gradio_chatagui-0.0.1.dist-info/METADATA
gradio_chatagui-0.0.1.dist-info/WHEEL
gradio_chatagui-0.0.1.dist-info/RECORD
